snp2str/__init__.py
snp2str/bases_coding.json
snp2str/exceptions.py
snp2str/process.py
snp2str/tests/__init__.py
snp2str-0.1.data/scripts/snp2str
snp2str-0.1.dist-info/METADATA
snp2str-0.1.dist-info/WHEEL
snp2str-0.1.dist-info/top_level.txt
snp2str-0.1.dist-info/RECORD
