Metadata-Version: 2.4
Name: snp2str
Version: 0.1
Summary: A Python tool for converting SNP genotype data in PED format to a format suitable for STRUCTURE analysis
Home-page: http://github.com/vladgheorghe/snp2str
Author: Vlad Gheorghe
Author-email: vlad.datapro@gmail.com
License: MIT
Classifier: Development Status :: 4 - Beta
Classifier: Intended Audience :: Science/Research
Classifier: Programming Language :: Python :: 3
Classifier: Topic :: Scientific/Engineering :: Bio-Informatics
Requires-Python: >=3.6
Requires-Dist: pandas==2.2.3
Dynamic: author
Dynamic: author-email
Dynamic: classifier
Dynamic: description
Dynamic: description-content-type
Dynamic: home-page
Dynamic: license
Dynamic: requires-dist
Dynamic: requires-python
Dynamic: summary
